chunker_cpp.cpython-312-darwin.so
chunker/chunker.cpp
chunker/chunker.h
chunker/test.py
cpp_chunker-0.1.4.dist-info/METADATA
cpp_chunker-0.1.4.dist-info/WHEEL
cpp_chunker-0.1.4.dist-info/top_level.txt
cpp_chunker-0.1.4.dist-info/RECORD
