Metadata-Version: 2.4
Name: cpp-chunker
Version: 0.1.4
Summary: C++ chunker
Author-email: Christian <alch.infoemail@gmail.com>
License-Expression: MIT
Classifier: Development Status :: 3 - Alpha
Classifier: Intended Audience :: Developers
Classifier: Programming Language :: Python :: 3
Classifier: Programming Language :: Python :: 3.7
Classifier: Programming Language :: Python :: 3.8
Classifier: Programming Language :: Python :: 3.9
Classifier: Programming Language :: Python :: 3.10
Classifier: Programming Language :: Python :: 3.11
Classifier: Programming Language :: Python :: 3.12
Classifier: Programming Language :: C++
Requires-Python: >=3.7
Requires-Dist: pybind11>=2.10.0
